odoo8_addon_stock_packaging_usability-8.0.1.0.0-py2.7-nspkg.pth
odoo_addons/stock_packaging_usability/__openerp__.py
odoo_addons/stock_packaging_usability/__init__.py
odoo_addons/stock_packaging_usability/README.rst
odoo_addons/stock_packaging_usability/i18n/stock_packaging_usability.pot
odoo_addons/stock_packaging_usability/i18n/fr.po
odoo_addons/stock_packaging_usability/wizard/stock_transfer_details.xml
odoo_addons/stock_packaging_usability/wizard/stock_transfer_details.py
odoo_addons/stock_packaging_usability/wizard/__init__.py
odoo8_addon_stock_packaging_usability-8.0.1.0.0.dist-info/top_level.txt
odoo8_addon_stock_packaging_usability-8.0.1.0.0.dist-info/WHEEL
odoo8_addon_stock_packaging_usability-8.0.1.0.0.dist-info/RECORD
odoo8_addon_stock_packaging_usability-8.0.1.0.0.dist-info/metadata.json
odoo8_addon_stock_packaging_usability-8.0.1.0.0.dist-info/DESCRIPTION.rst
odoo8_addon_stock_packaging_usability-8.0.1.0.0.dist-info/METADATA
odoo8_addon_stock_packaging_usability-8.0.1.0.0.dist-info/namespace_packages.txt
